jupyter_anywidget_graphviz/__init__.py
jupyter_anywidget_graphviz/magics.py
jupyter_anywidget_graphviz/panel.py
jupyter_anywidget_graphviz/static/audio.js
jupyter_anywidget_graphviz/static/graphviz.css
jupyter_anywidget_graphviz/static/graphviz.js
jupyter_anywidget_graphviz/static/uuid.js
jupyter_anywidget_graphviz/static/widget.css
jupyter_anywidget_graphviz/static/widget.js
jupyter_anywidget_graphviz-0.1.8.dist-info/METADATA
jupyter_anywidget_graphviz-0.1.8.dist-info/WHEEL
jupyter_anywidget_graphviz-0.1.8.dist-info/RECORD
