Metadata-Version: 2.3
Name: jupyter_anywidget_graphviz
Version: 0.1.8
Requires-Dist: anywidget
Provides-Extra: dev
Requires-Dist: jupyterlab; extra == 'dev'
Requires-Dist: watchfiles; extra == 'dev'
